neurograph/__init__.py
neurograph/v1/__init__.py
neurograph/v1/api_client.py
neurograph/v1/api_response.py
neurograph/v1/configuration.py
neurograph/v1/exceptions.py
neurograph/v1/py.typed
neurograph/v1/rest.py
neurograph/v1/api/__init__.py
neurograph/v1/api/admin_api.py
neurograph/v1/api/authentication_api.py
neurograph/v1/api/client_api.py
neurograph/v1/api/client_metadata_api.py
neurograph/v1/api/dagster_api.py
neurograph/v1/api/knowledge_api.py
neurograph/v1/api/knowledge_extract_api.py
neurograph/v1/api/lookup_api.py
neurograph/v1/api/organization_api.py
neurograph/v1/api/organization_metadata_api.py
neurograph/v1/api/persona_api.py
neurograph/v1/api/pixel_api.py
neurograph/v1/api/reporting_api.py
neurograph/v1/api/reports_api.py
neurograph/v1/api/signal_api.py
neurograph/v1/api/user_api.py
neurograph/v1/api/workbench_api.py
neurograph/v1/models/__init__.py
neurograph/v1/models/admin_permission_response.py
neurograph/v1/models/admin_reset_password_request.py
neurograph/v1/models/admin_reset_password_response.py
neurograph/v1/models/admin_set_permission_request.py
neurograph/v1/models/admin_upsert_user_request.py
neurograph/v1/models/admin_upsert_user_response.py
neurograph/v1/models/admin_user.py
neurograph/v1/models/admin_user_detail_response.py
neurograph/v1/models/admin_users_get_many_response.py
neurograph/v1/models/admin_users_org_response.py
neurograph/v1/models/auth_service_token_request.py
neurograph/v1/models/auth_service_token_response.py
neurograph/v1/models/auth_test_service_token_request.py
neurograph/v1/models/auth_test_service_token_response.py
neurograph/v1/models/auth_test_token_response.py
neurograph/v1/models/client_client.py
neurograph/v1/models/client_delete_metadata_request.py
neurograph/v1/models/client_get_detail_response.py
neurograph/v1/models/client_get_many_response.py
neurograph/v1/models/client_healthcheck_create_request.py
neurograph/v1/models/client_healthcheck_response.py
neurograph_core-1.202601291819.dist-info/METADATA
neurograph_core-1.202601291819.dist-info/WHEEL
neurograph_core-1.202601291819.dist-info/top_level.txt
neurograph_core-1.202601291819.dist-info/RECORD
