Metadata-Version: 2.4
Name: neurograph-core
Version: 1.202601291819
Summary: Neurograph Core
Home-page: 
Author: Neurograph Development Team
Author-email: team@openapitools.org
License: (c) Neurograph 2025. All rights reserved.
Project-URL: Repository, https://github.com/NeuroGraph-AI/core/
Keywords: OpenAPI,OpenAPI-Generator,Neurograph Core
Classifier: Programming Language :: Python :: 3
Classifier: Programming Language :: Python :: 3 :: Only
Classifier: Programming Language :: Python :: 3.9
Classifier: Programming Language :: Python :: 3.10
Classifier: Programming Language :: Python :: 3.11
Classifier: Programming Language :: Python :: 3.12
Classifier: Typing :: Typed
Classifier: Intended Audience :: Developers
Classifier: Topic :: Software Development :: Libraries
Classifier: License :: Other/Proprietary License
Requires-Python: >=3.9
Requires-Dist: urllib3<3.0.0,>=2.1.0
Requires-Dist: python-dateutil>=2.8.2
Requires-Dist: pydantic>=2
Requires-Dist: typing-extensions>=4.7.1
Dynamic: author-email
